CHANGES.rst
CONTRIBUTORS.rst
LICENSE.txt
MANIFEST.in
README.rst
setup.py
docs/__init__.py
src/edeposit/__init__.py
src/edeposit.amqp.pdfgen.egg-info/PKG-INFO
src/edeposit.amqp.pdfgen.egg-info/SOURCES.txt
src/edeposit.amqp.pdfgen.egg-info/dependency_links.txt
src/edeposit.amqp.pdfgen.egg-info/namespace_packages.txt
src/edeposit.amqp.pdfgen.egg-info/not-zip-safe
src/edeposit.amqp.pdfgen.egg-info/requires.txt
src/edeposit.amqp.pdfgen.egg-info/top_level.txt
src/edeposit/amqp/__init__.py
src/edeposit/amqp/pdfgen/__init__.py
src/edeposit/amqp/pdfgen/specialization.py
src/edeposit/amqp/pdfgen/translator.py
src/edeposit/amqp/pdfgen/resources/Licencni_smlouva_o_dodavani_elektronickych_publikaci_a_jejich_uziti.rst
src/edeposit/amqp/pdfgen/resources/header_logo.png
src/edeposit/amqp/pdfgen/resources/review.rst
src/edeposit/amqp/pdfgen/resources/review_style.json
src/edeposit/amqp/pdfgen/resources/style.json
src/edeposit/amqp/pdfgen/structures/__init__.py
src/edeposit/amqp/pdfgen/structures/requests.py
src/edeposit/amqp/pdfgen/structures/requests_generator.py
src/edeposit/amqp/pdfgen/structures/responses.py
tests/example.pdf
tests/example_metadata.json
tests/review_example.pdf
tests/test_gen_review.py
tests/test_translator.py
tests/__pycache__/test_gen_review.cpython-27-PYTEST.pyc
tests/__pycache__/test_translator.cpython-27-PYTEST.pyc